MANIFEST.in
NEWS.rst
README.rst
requirements.txt
setup.cfg
setup.py
test-requirements.txt
build_scripts/__init__.py
build_scripts/version.py
period/RELEASE-VERSION
period/__init__.py
period/commands.py
period/main.py
period.egg-info/PKG-INFO
period.egg-info/SOURCES.txt
period.egg-info/dependency_links.txt
period.egg-info/not-zip-safe
period.egg-info/requires.txt
period.egg-info/top_level.txt
period/tests/__init__.py