Metadata-Version: 1.1
Name: period
Version: 0.6.1
Summary: basic time period checking libary for Python
Home-page: https://github.com/LinkCareServices/period
Author: William S. Annis
Author-email: UNKNOWN
License: Artistic License 2.0
Keywords: date time period
Platform: UNKNOWN
Classifier: Development Status :: 2 - Pre-Alpha
Classifier: Intended Audience :: Developers
Classifier: License :: OSI Approved :: Artistic License
Classifier: Operating System :: POSIX :: Linux
Classifier: Programming Language :: Python
Classifier: Programming Language :: Python :: 2.7
Classifier: Programming Language :: Python :: 3.4
Classifier: Topic :: Software Development :: Libraries :: Python Modules
